scrapy_statsd/__init__.py
scrapy_statsd/statscollectors.py
scrapy_statsd/tests/__init__.py
scrapy_statsd/tests/statscollectors_test.py
scrapy_statsd/tests/test_project/__init__.py
scrapy_statsd/tests/test_project/test_project/__init__.py
scrapy_statsd/tests/test_project/test_project/items.py
scrapy_statsd/tests/test_project/test_project/pipelines.py
scrapy_statsd/tests/test_project/test_project/settings.py
scrapy_statsd/tests/test_project/test_project/spiders/__init__.py
scrapy_statsd/tests/test_project/test_project/spiders/test.py
scrapy_statsd-1.0.0a1.dist-info/DESCRIPTION.rst
scrapy_statsd-1.0.0a1.dist-info/METADATA
scrapy_statsd-1.0.0a1.dist-info/RECORD
scrapy_statsd-1.0.0a1.dist-info/WHEEL
scrapy_statsd-1.0.0a1.dist-info/metadata.json
scrapy_statsd-1.0.0a1.dist-info/top_level.txt
